plover_practice_plugin/__init__.py
plover_practice_plugin/command.py
plover_practice_plugin/extension.py
plover_practice_plugin/meta.py
plover_practice_plugin-0.0.1.dist-info/LICENSE.txt
plover_practice_plugin-0.0.1.dist-info/METADATA
plover_practice_plugin-0.0.1.dist-info/WHEEL
plover_practice_plugin-0.0.1.dist-info/entry_points.txt
plover_practice_plugin-0.0.1.dist-info/top_level.txt
plover_practice_plugin-0.0.1.dist-info/zip-safe
plover_practice_plugin-0.0.1.dist-info/RECORD
